{
  "carediscover": {
    "informationItems": [
      {
        "icon": "age",
        "label": "가입연령",
        "description": "만 65세까지 가입 가능"
      },
      {
        "icon": "duration",
        "label": "보험기간",
        "description": "최대 3년까지"
      },
      {
        "icon": "region",
        "label": "보험지역",
        "description": "모국을 제외한 전세계"
      }
    ],
    "pricing": {
      "labels": [
        "나이(만)",
        "기본보험료\n_(10일까지 같은 금액)_",
        "일일연장 보험료"
      ],
      "items": [
        [
          "0-35세",
          "13.9EUR\n*17,817원*",
          "1.39EUR/일\n*1,781원/일*"
        ],
        [
          "36-65세",
          "24.9EUR\n*31,917원*",
          "2.49EUR/일\n*3,191원/일*"
        ]
      ]
    }
  },
  "carecollege": {
    "informationItems": [
      {
        "icon": "target",
        "label": "가입대상",
        "description": "유학생(학업을 목적으로 출국),\n워킹홀리데이"
      },
      {
        "icon": "age",
        "label": "가입연령",
        "description": "만 12세~35세"
      },
      {
        "icon": "duration",
        "label": "보험기간",
        "description": "최대 5년까지"
      },
      {
        "icon": "region",
        "label": "보험지역",
        "description": "유럽연합(EU),\n솅겐지역(Schegen Area)"
      }
    ],
    "pricing": {
      "labels": [
        "종류",
        "BASIC",
        "COMPORT",
        "PREMIUM"
      ],
      "items": [
        [
          "전세계 긴급서비스",
          "(V)",
          "(V)",
          "(V)"
        ],
        [
          "입원의료비 (다인실)",
          "(V)",
          "(V)",
          "(V)"
        ],
        [
          "입원일당",
          "(X)",
          "(X)",
          "일당 100€"
        ],
        [
          "처방약",
          "(V)",
          "(V)",
          "(V)"
        ],
        [
          "임신검사/치료",
          "(V)\n_자부담 50€_",
          "(V)\n_자부담 25€_",
          "(V)"
        ],
        [
          "치료비",
          "정가 1.8배까지",
          "정가 2.3배까지",
          "정가 2.3배까지"
        ],
        [
          "처방된 보조기구",
          "(V)\n_(250€까지)_",
          "(V)\n_(250€까지)_",
          "(V)\n_(100%)_"
        ],
        [
          "모국 송환비",
          "(V)\n_(10,000€까지)_",
          "(V)\n_(100%)_",
          "(V)\n_(100%)_"
        ],
        [
          "진통관련 치과비",
          "(V)\n_(250€초과분 50%)_",
          "(V)\n_(250€초과분 50%)_",
          "(V)\n_(100%)_"
        ],
        [
          "임플란트",
          "(X)",
          "(V)\n_(500€까지, 50%)_",
          "(V)\n_(1,000€까지, 70%)_"
        ],
        [
          "사고관련 임플란트",
          "(X)",
          "(X)",
          "(V)\n_(2,500€)_"
        ],
        [
          "시신후송 장례비",
          "(V)\n_(25,000€까지)_",
          "(V)\n_(25,000€까지)_",
          "(V)\n_(25,000€까지)_"
        ],
        [
          "본인부담금",
          "건당 50€",
          "임신만",
          "(X)"
        ],
        [
          "해지 후 보장기간",
          "4주",
          "4주",
          "8주"
        ],
        [
          "연간 무사고 환급",
          "(X)",
          "1.5개월치 환급",
          "2개월치 환급"
        ],
        [
          "시력보조기",
          "(X)",
          "(X)",
          "(V)\n_(100€까지)_"
        ],
        [
          "보험기간\n18개월까지",
          "28EUR\n35,890원",
          "35EUR\n44,863원",
          "63EUR\n80,753원"
        ],
        [
          "보험기간\n9개월 이후",
          "51EUR\n65,372원",
          "59EUR\n75,626원",
          "83EUR\n106,390원"
        ]
      ]
    }
  },
  "privateinsurance": {
    "informationItems": [
      {
        "icon": "age",
        "label": "가입연령",
        "description": "만 65세까지 가입 가능"
      },
      {
        "icon": "duration",
        "label": "보험기간",
        "description": "최소 6개월부터 최대 5년까지"
      }
    ],
    "pricing": {
      "labels": [
        "종류",
        "BASIC",
        "COMPORT",
        "PREMIUM"
      ],
      "items": [
        [
          "연간부담금",
          "500EUR",
          "500EUR",
          "없음"
        ],
        [
          "월 보험료",
          "134EUR",
          "235EUR",
          "353.98EUR"
        ]
      ]
    }
  }
}
